Metadata-Version: 2.1
Name: sambhawithawa
Version: 0.1
Summary: Gaussian and Binomial distributions
Home-page: UNKNOWN
Author: Hasarindu Perera
License: UNKNOWN
Platform: UNKNOWN
